tframex/__init__.py
tframex/app.py
tframex/cli.py
tframex/agents/__init__.py
tframex/agents/base.py
tframex/agents/llm_agent.py
tframex/agents/tool_agent.py
tframex/enterprise/__init__.py
tframex/enterprise/analytics.py
tframex/enterprise/app.py
tframex/enterprise/config.py
tframex/enterprise/integration.py
tframex/enterprise/models.py
tframex/enterprise/tracing.py
tframex/enterprise/metrics/__init__.py
tframex/enterprise/metrics/base.py
tframex/enterprise/metrics/custom.py
tframex/enterprise/metrics/manager.py
tframex/enterprise/metrics/opentelemetry.py
tframex/enterprise/metrics/prometheus.py
tframex/enterprise/metrics/statsd.py
tframex/enterprise/security/__init__.py
tframex/enterprise/security/audit.py
tframex/enterprise/security/auth.py
tframex/enterprise/security/middleware.py
tframex/enterprise/security/rbac.py
tframex/enterprise/security/session.py
tframex/enterprise/storage/__init__.py
tframex/enterprise/storage/base.py
tframex/enterprise/storage/factory.py
tframex/enterprise/storage/memory.py
tframex/enterprise/storage/migrations.py
tframex/enterprise/storage/postgresql.py
tframex/enterprise/storage/redis.py
tframex/enterprise/storage/s3.py
tframex/enterprise/storage/sqlite.py
tframex/flows/__init__.py
tframex/flows/flow_context.py
tframex/flows/flows.py
tframex/mcp/__init__.py
tframex/mcp/capabilities.py
tframex/mcp/config.py
tframex/mcp/content.py
tframex/mcp/manager.py
tframex/mcp/meta_tools.py
tframex/mcp/notifications.py
tframex/mcp/progress.py
tframex/mcp/roots.py
tframex/mcp/sampling.py
tframex/mcp/server_connector.py
tframex/mcp/sse_transport.py
tframex/models/__init__.py
tframex/models/primitives.py
tframex/patterns/__init__.py
tframex/patterns/patterns.py
tframex/util/__init__.py
tframex/util/engine.py
tframex/util/llms.py
tframex/util/memory.py
tframex/util/tools.py
tframex/util/logging/__init__.py
tframex/util/logging/logging_config.py
tframex-1.1.0.dist-info/licenses/LICENSE
tframex-1.1.0.dist-info/METADATA
tframex-1.1.0.dist-info/WHEEL
tframex-1.1.0.dist-info/entry_points.txt
tframex-1.1.0.dist-info/top_level.txt
tframex-1.1.0.dist-info/RECORD
