Metadata-Version: 2.4
Name: tframex
Version: 1.1.0
Summary: A framework for building agentic systems with large language models.
Author: TesslateAI
Author-email: Manav Majumdar <manav@tesslate.com>, Sanjit Verma <sanjitverma@tesslate.com>, Prajwal Moharana <pmoharana@tesslate.com>
License: MIT
Project-URL: Homepage, https://github.com/TesslateAI/TFrameX
Project-URL: Repository, https://github.com/TesslateAI/TFrameX
Classifier: Programming Language :: Python :: 3
Classifier: Programming Language :: Python :: 3.8
Classifier: Programming Language :: Python :: 3.9
Classifier: Programming Language :: Python :: 3.10
Classifier: Programming Language :: Python :: 3.11
Classifier: Operating System :: OS Independent
Classifier: Intended Audience :: Developers
Classifier: Topic :: Software Development :: Libraries :: Python Modules
Classifier: Topic :: Scientific/Engineering :: Artificial Intelligence
Requires-Python: >=3.8
License-File: LICENSE
Requires-Dist: httpx>=0.25.0
Requires-Dist: python-dotenv>=1.0.0
Requires-Dist: PyYAML>=6.0.1
Requires-Dist: openai>=1.0.0
Requires-Dist: pydantic>=2.0.0
Requires-Dist: aiohttp>=3.0.0
Requires-Dist: mcp
Provides-Extra: examples
Requires-Dist: Flask>=3.0.0; extra == "examples"
Provides-Extra: web
Requires-Dist: Flask>=3.0.0; extra == "web"
Provides-Extra: dev
Requires-Dist: black>=24.3.0; extra == "dev"
Requires-Dist: isort>=5.13.2; extra == "dev"
Requires-Dist: pre-commit>=3.3.0; extra == "dev"
Provides-Extra: enterprise
Requires-Dist: asyncpg>=0.27.0; extra == "enterprise"
Requires-Dist: aioboto3>=11.0.0; extra == "enterprise"
Requires-Dist: redis[hiredis]>=5.0.0; extra == "enterprise"
Dynamic: license-file
